csv_permissions/__init__.py
csv_permissions/apps.py
csv_permissions/evaluators.py
csv_permissions/legacy.py
csv_permissions/permissions.py
csv_permissions/test_utils.py
csv_permissions/types.py
django_csvpermissions-0.3.0.dist-info/METADATA
django_csvpermissions-0.3.0.dist-info/WHEEL
django_csvpermissions-0.3.0.dist-info/licenses/LICENSE
django_csvpermissions-0.3.0.dist-info/RECORD
