Metadata-Version: 2.4
Name: django_csvpermissions
Version: 0.3.0
Summary: CSV Based Permissions Module for Django
License: BSD-2-Clause
License-File: LICENSE
Keywords: django,permission,alliance,alliancesoftware
Author: Alliance Software
Author-email: support@alliancesoftware.com.au
Requires-Python: >=3.6,<4.0
Classifier: License :: OSI Approved :: BSD License
Classifier: Programming Language :: Python :: 3
Classifier: Programming Language :: Python :: 3.6
Classifier: Programming Language :: Python :: 3.7
Classifier: Programming Language :: Python :: 3.8
Classifier: Programming Language :: Python :: 3.9
Classifier: Programming Language :: Python :: 3.10
Classifier: Programming Language :: Python :: 3.11
Classifier: Programming Language :: Python :: 3.12
Classifier: Programming Language :: Python :: 3.13
Classifier: Programming Language :: Python :: 3.14
Requires-Dist: Django (>=2.2)
